MANIFEST.in
README.md
setup.py
bin/pyside6-live-coding
examples/integrated/live.qml
examples/integrated/main.py
examples/integrated/main.qml
examples/integrated/myapp/MainPanel.qml
examples/integrated/myapp/qmldir
examples/standalone/MainScreen.qml
examples/standalone/qmldir
examples/standalone/module/__init__.py
examples/standalone/module/calculator.py
src/pyside6_live_coding/FileSelectionDialog.qml
src/pyside6_live_coding/LiveCodingPanel.qml
src/pyside6_live_coding/__init__.py
src/pyside6_live_coding/filewatcher.py
src/pyside6_live_coding/gui.py
src/pyside6_live_coding/icon.png
src/pyside6_live_coding/live.qml
src/pyside6_live_coding/live_coding_helper.py
src/pyside6_live_coding/moduleloader.py
src/pyside6_live_coding/projectbrowser.py
src/pyside6_live_coding/pythonreloader.py
src/pyside6_live_coding/qmldir
src/pyside6_live_coding/register_qml_types.py
src/pyside6_live_coding.egg-info/PKG-INFO
src/pyside6_live_coding.egg-info/SOURCES.txt
src/pyside6_live_coding.egg-info/dependency_links.txt
src/pyside6_live_coding.egg-info/requires.txt
src/pyside6_live_coding.egg-info/top_level.txt