Metadata-Version: 2.1
Name: pyside6-live-coding
Version: 1.0.1
Summary: Live coding for Python, Qt and QML
Home-page: https://github.com/machinekoder/pyside6-live-coding/
Author: Alexander Rössler
Author-email: alex@machinekoder.com
License: MIT
Platform: UNKNOWN
Provides-Extra: dev
